cmdpedia_generator/__init__.py
cmdpedia_generator/__main__.py
cmdpedia_generator/core.py
cmdpedia_generator/programs/__init__.py
cmdpedia_generator/programs/click.py
cmdpedia_generator/templates/index.html
cmdpedia_generator-0.0.1a2.dist-info/LICENSE
cmdpedia_generator-0.0.1a2.dist-info/METADATA
cmdpedia_generator-0.0.1a2.dist-info/WHEEL
cmdpedia_generator-0.0.1a2.dist-info/entry_points.txt
cmdpedia_generator-0.0.1a2.dist-info/top_level.txt
cmdpedia_generator-0.0.1a2.dist-info/RECORD
