Metadata-Version: 2.1
Name: cmdpedia_generator
Version: 0.0.1a2
Summary: A tool for generating command documentation from Python CLI applications.
Home-page: https://github.com/derekology/cmdpedia-generator
Author: Derek Woo
Author-email: me@derekw.co
Classifier: Programming Language :: Python :: 3
Classifier: Operating System :: OS Independent
Requires-Python: >=3.6
License-File: LICENSE
Requires-Dist: click
